MANIFEST
reload.sh
setup.py
upload.sh
azure_sql/README.md
azure_sql/__init__.py
azure_sql/lib.py
azure_sql.egg-info/PKG-INFO
azure_sql.egg-info/SOURCES.txt
azure_sql.egg-info/dependency_links.txt
azure_sql.egg-info/requires.txt
azure_sql.egg-info/top_level.txt
azure_sql/.idea/.gitignore
azure_sql/.idea/azure_sql.iml
azure_sql/.idea/misc.xml
azure_sql/.idea/modules.xml
azure_sql/.idea/vcs.xml
azure_sql/.idea/inspectionProfiles/profiles_settings.xml
azure_sql/__pycache__/__init__.cpython-37.pyc
azure_sql/__pycache__/countries.cpython-37.pyc
azure_sql/__pycache__/lib.cpython-37.pyc