Metadata-Version: 1.1
Name: azure-sql
Version: 1.8
Summary: Azure Database done easy
Home-page: https://github.com/user/reponame
Author: Ognjen/ShinSheel
Author-email: vlad.g@simporter.com
License: MIT
Download-URL: https://github.com/user/reponame/archive/v_01.tar.gz
Keywords: Azure,SQL,third party,MySQL,Transact SQL
Platform: UNKNOWN
Classifier: Development Status :: 3 - Alpha
Classifier: Intended Audience :: Developers
Classifier: Topic :: Software Development :: Build Tools
Classifier: License :: OSI Approved :: MIT License
Classifier: Programming Language :: Python :: 3
Classifier: Programming Language :: Python :: 3.4
Classifier: Programming Language :: Python :: 3.5
Classifier: Programming Language :: Python :: 3.6
